webstats/__init__.py
webstats/admin.py
webstats/apps.py
webstats/migrations/0001_initial.py
webstats/migrations/__init__.py
webstats/mixins.py
webstats/models.py
webstats/tests.py
webstats/urls.py
webstats/views.py
django_webstats-0.1.0.dist-info/LICENSE
django_webstats-0.1.0.dist-info/METADATA
django_webstats-0.1.0.dist-info/WHEEL
django_webstats-0.1.0.dist-info/RECORD
