Metadata-Version: 2.1
Name: django-webstats
Version: 0.1.0
Summary: Simple functionality to record django view visits (IP Address, URLs, User info)
License: MIT
Author: Harlin Seritt
Author-email: harlin.seritt@gmail.com
Requires-Python: >=3.12,<4.0
Classifier: License :: OSI Approved :: MIT License
Classifier: Programming Language :: Python :: 3
Classifier: Programming Language :: Python :: 3.12
Requires-Dist: django (>=5.0.4,<6.0.0)
